wp_engine_api/__init__.py
wp_engine_api/client.py
wp_engine_api/config.py
wp_engine_api/endpoints.py
wp_engine_api/exceptions.py
wp_engine_api/models.py
wp_engine_api/rate_limiter.py
wp_engine_api/generated/__init__.py
wp_engine_api/generated/api_client.py
wp_engine_api/generated/api_response.py
wp_engine_api/generated/configuration.py
wp_engine_api/generated/exceptions.py
wp_engine_api/generated/py.typed
wp_engine_api/generated/rest.py
wp_engine_api/generated/api/__init__.py
wp_engine_api/generated/api/account_api.py
wp_engine_api/generated/api/account_user_api.py
wp_engine_api/generated/api/backup_api.py
wp_engine_api/generated/api/cache_api.py
wp_engine_api/generated/api/cdn_api.py
wp_engine_api/generated/api/domain_api.py
wp_engine_api/generated/api/install_api.py
wp_engine_api/generated/api/site_api.py
wp_engine_api/generated/api/ssh_key_api.py
wp_engine_api/generated/api/status_api.py
wp_engine_api/generated/api/swagger_api.py
wp_engine_api/generated/api/user_api.py
wp_engine_api/generated/models/__init__.py
wp_engine_api/generated/models/account.py
wp_engine_api/generated/models/account_user.py
wp_engine_api/generated/models/account_user_installs_inner.py
wp_engine_api/generated/models/authentication_error_response.py
wp_engine_api/generated/models/backup.py
wp_engine_api/generated/models/bad_request_error_response.py
wp_engine_api/generated/models/check_status429_response.py
wp_engine_api/generated/models/create_account_user201_response.py
wp_engine_api/generated/models/create_account_user_request.py
wp_engine_api/generated/models/create_account_user_request_user.py
wp_engine_api/generated/models/create_backup_request.py
wp_engine_api/generated/models/create_bulk_domains_request.py
wp_engine_api/generated/models/create_bulk_domains_request_domains_inner.py
wp_engine_api/generated/models/create_domain_request.py
wp_engine_api/generated/models/create_install_request.py
wp_engine_api/generated/models/create_site_request.py
wp_engine_api_python-0.0.2.dist-info/LICENSE
wp_engine_api_python-0.0.2.dist-info/METADATA
wp_engine_api_python-0.0.2.dist-info/WHEEL
wp_engine_api_python-0.0.2.dist-info/top_level.txt
wp_engine_api_python-0.0.2.dist-info/RECORD
