Metadata-Version: 2.1
Name: wp-engine-api-python
Version: 0.0.2
Summary: WP Engine API SDK for Python
Home-page: https://github.com/jpollock/wp-engine-api-python
Author: Jeremy Pollock
Author-email: Jeremy Pollock <jeremy.pollock@wpengine.com>
License: MIT
Project-URL: Documentation, https://wpengineapi.com/docs
Project-URL: Source, https://github.com/jpollock/wp-engine-api-python
Project-URL: Bug Reports, https://github.com/jpollock/wp-engine-api-python/issues
Keywords: wpengine,wordpress,api,sdk
Classifier: Development Status :: 3 - Alpha
Classifier: Intended Audience :: Developers
Classifier: License :: OSI Approved :: MIT License
Classifier: Operating System :: OS Independent
Classifier: Programming Language :: Python :: 3
Classifier: Programming Language :: Python :: 3.8
Classifier: Programming Language :: Python :: 3.9
Classifier: Programming Language :: Python :: 3.10
Classifier: Programming Language :: Python :: 3.11
Classifier: Topic :: Software Development :: Libraries :: Python Modules
Requires-Python: >=3.8
License-File: LICENSE
Requires-Dist: requests>=2.25.0
Requires-Dist: python-dateutil>=2.8.0
Requires-Dist: urllib3>=1.26.0
Requires-Dist: pydantic>=2.0.0
Requires-Dist: typing-extensions>=4.0.0
Requires-Dist: python-dotenv>=1.0.0
Provides-Extra: dev
Requires-Dist: pytest>=7.0.0; extra == "dev"
Requires-Dist: pytest-cov>=4.0.0; extra == "dev"
Requires-Dist: black>=22.0.0; extra == "dev"
Requires-Dist: isort>=5.0.0; extra == "dev"
Requires-Dist: mypy>=1.0.0; extra == "dev"
Requires-Dist: flake8>=6.0.0; extra == "dev"
